IPToolz/__init__.py
IPToolz-1.1.0.dist-info/LICENSE.txt
IPToolz-1.1.0.dist-info/METADATA
IPToolz-1.1.0.dist-info/WHEEL
IPToolz-1.1.0.dist-info/top_level.txt
IPToolz-1.1.0.dist-info/RECORD
